LICENSE
MANIFEST.in
README.md
pyproject.toml
requirements.txt
setup.py
test-requirements.txt
sacad/__init__.py
sacad/__main__.py
sacad/colored_logging.py
sacad/cover.py
sacad/http_helpers.py
sacad/mkstemp_ctx.py
sacad/rate_watcher.py
sacad/recurse.py
sacad/redo.py
sacad/tqdm_logging.py
sacad.egg-info/PKG-INFO
sacad.egg-info/SOURCES.txt
sacad.egg-info/dependency_links.txt
sacad.egg-info/entry_points.txt
sacad.egg-info/requires.txt
sacad.egg-info/top_level.txt
sacad/sources/__init__.py
sacad/sources/base.py
sacad/sources/deezer.py
sacad/sources/discogs.py
sacad/sources/itunes.py
sacad/sources/lastfm.py