Metadata-Version: 2.4
Name: sacad
Version: 2.8.3
Summary: Search and download music album covers
Home-page: https://github.com/desbma/sacad
Download-URL: https://github.com/desbma/sacad/archive/2.8.3.tar.gz
Author: desbma
Keywords: download,album,cover,art,albumart,music
Classifier: Development Status :: 5 - Production/Stable
Classifier: Environment :: Console
Classifier: Intended Audience :: End Users/Desktop
Classifier: License :: OSI Approved :: Mozilla Public License 2.0 (MPL 2.0)
Classifier: Natural Language :: English
Classifier: Operating System :: OS Independent
Classifier: Programming Language :: Python
Classifier: Programming Language :: Python :: 3
Classifier: Programming Language :: Python :: 3 :: Only
Classifier: Programming Language :: Python :: 3.10
Classifier: Programming Language :: Python :: 3.11
Classifier: Programming Language :: Python :: 3.12
Classifier: Programming Language :: Python :: 3.13
Classifier: Programming Language :: Python :: 3.14
Classifier: Topic :: Internet :: WWW/HTTP
Classifier: Topic :: Multimedia :: Graphics
Classifier: Topic :: Utilities
License-File: LICENSE
Requires-Dist: aiohttp>=3.6
Requires-Dist: appdirs>=1.4.0
Requires-Dist: bitarray>=2.0.0
Requires-Dist: cssselect>=1.1.0
Requires-Dist: lxml>=4.0.0
Requires-Dist: mutagen>=1.31
Requires-Dist: pillow>=8.0.0
Requires-Dist: tqdm>=4.28.1
Requires-Dist: unidecode>=1.1.1
Requires-Dist: web_cache>=1.1.0
Dynamic: author
Dynamic: classifier
Dynamic: description
Dynamic: description-content-type
Dynamic: download-url
Dynamic: home-page
Dynamic: keywords
Dynamic: license-file
Dynamic: requires-dist
Dynamic: summary
